{
	"display": {
		"icon": {
			"item": "minecraft:echo_shard",
			"nbt": "{Enchantments:[{}]}"
		},
		"title": {
			"translate": "What did it cost?"
		},
		"description": {
			"translate": "Charge a Void Shard by killing an Ender Dragon and claiming its soul\n[Must be in mainhand or offhand]"
		},
		"frame": "task",
		"show_toast": true,
		"announce_to_chat": true,
		"hidden": false
	},
	"parent": "voidborn:progression/obtain_void_shard",
	"criteria": {
		"requirement": {
			"trigger": "minecraft:inventory_changed",
			"conditions": {
				"items": [
					{
						"nbt": "{voidborn:{item:\"void_shard\",durability:5}}"
					}
				]
			}
		}
	}
}
